[
    {
        "ID": "furiosa_head",
        "Name": "Furiosa",
        "Shortname": "F",
        "Description": "Are you really reading this description dumbass?",
        "AddtoPlayer": true,
        "Side": ["Usec", "Bear"]
    },
    {
        "ID": "lara_head",
        "Name": "Lara",
        "Shortname": "RH",
        "Description": "Are you really reading this description dumbass?",
        "AddtoPlayer": true,
        "Side": ["Usec", "Bear"]
    },
    {
        "ID": "elena_head",
        "Name": "Elena",
        "Shortname": "El",
        "Description": "Are you really reading this description dumbass?",
        "AddtoPlayer": true,
        "Side": ["Usec", "Bear"]
    },
    {
        "ID": "laura_head",
        "Name": "Laura",
        "Shortname": "L",
        "Description": "Are you really reading this description dumbass?",
        "AddtoPlayer": true,
        "Side": ["Usec", "Bear"]
    },
    {
        "ID": "eivor_head",
        "Name": "Eivor",
        "Shortname": "Eiv",
        "Description": "Are you really reading this description dumbass?",
        "AddtoPlayer": true,
        "Side": ["Usec", "Bear"]
    },
    {
        "ID": "valeria_1_head",
        "Name": "Valeria",
        "Shortname": "Val",
        "Description": "Are you really reading this description dumbass?",
        "AddtoPlayer": true,
        "Side": ["Usec", "Bear"]
    },
    {
        "ID": "valeria_12_head",
        "Name": "Valeria (alt)",
        "Shortname": "Val",
        "Description": "Are you really reading this description dumbass?",
        "AddtoPlayer": true,
        "Side": ["Usec", "Bear"]
    },
    {
        "ID": "roze_1_1_head",
        "Name": "Roze",
        "Shortname": "Ro",
        "Description": "Are you really reading this description dumbass?",
        "AddtoPlayer": true,
        "Side": ["Usec", "Bear"]
    },
    {
        "ID": "mila_11_head",
        "Name": "Mila",
        "Shortname": "Mi",
        "Description": "Are you really reading this description dumbass?",
        "AddtoPlayer": true,
        "Side": ["Usec", "Bear"]
    },
    {
        "ID": "callisto_21_head",
        "Name": "Callisto",
        "Shortname": "Cal",
        "Description": "Are you really reading this description dumbass?",
        "AddtoPlayer": true,
        "Side": ["Usec", "Bear"]
    },
    {
        "ID": "zoey_head",
        "Name": "Zoey",
        "Shortname": "Z",
        "Description": "Are you really reading this description dumbass?",
        "AddtoPlayer": true,
        "Side": ["Usec", "Bear"]
    }
]